garak_sdk/__init__.py
garak_sdk/auth.py
garak_sdk/client.py
garak_sdk/exceptions.py
garak_sdk/models.py
garak_sdk/utils.py
garak_sdk/resources/__init__.py
garak_sdk/resources/metadata.py
garak_sdk/resources/reports.py
garak_sdk/resources/scans.py
garak_sdk-1.0.4.dist-info/licenses/LICENSE
garak_sdk-1.0.4.dist-info/METADATA
garak_sdk-1.0.4.dist-info/WHEEL
garak_sdk-1.0.4.dist-info/top_level.txt
garak_sdk-1.0.4.dist-info/RECORD
