Metadata-Version: 2.4
Name: garak-sdk
Version: 1.0.4
Summary: Python client library for the Garak AI Security Platform
Home-page: https://github.com/Garak-inc/garak-python-sdk
Author: Garak Security
Author-email: Garak Security <support@getgarak.com>
License: MIT
Project-URL: Homepage, https://garaksecurity.com
Project-URL: Documentation, https://docs.garaksecurity.com
Project-URL: Repository, https://github.com/Garak-inc/garak-python-sdk
Keywords: security,ai,llm,vulnerability,scanning,garak,red-team
Classifier: Development Status :: 4 - Beta
Classifier: Intended Audience :: Developers
Classifier: Topic :: Software Development :: Libraries :: Python Modules
Classifier: Topic :: Security
Classifier: License :: OSI Approved :: MIT License
Classifier: Programming Language :: Python :: 3
Classifier: Programming Language :: Python :: 3.8
Classifier: Programming Language :: Python :: 3.9
Classifier: Programming Language :: Python :: 3.10
Classifier: Programming Language :: Python :: 3.11
Classifier: Programming Language :: Python :: 3.12
Requires-Python: >=3.8
License-File: LICENSE
Requires-Dist: requests>=2.31.0
Requires-Dist: pydantic>=2.0.0
Provides-Extra: dev
Requires-Dist: pytest>=7.0.0; extra == "dev"
Requires-Dist: pytest-cov>=4.0.0; extra == "dev"
Requires-Dist: black>=23.0.0; extra == "dev"
Requires-Dist: flake8>=6.0.0; extra == "dev"
Requires-Dist: mypy>=1.0.0; extra == "dev"
Requires-Dist: isort>=5.12.0; extra == "dev"
Provides-Extra: dotenv
Requires-Dist: python-dotenv>=1.0.0; extra == "dotenv"
Dynamic: author
Dynamic: home-page
Dynamic: license-file
Dynamic: requires-python
